{"appname": "Matious", "email": "aicha@gmail.com", "iconcolor": "Color(0xff008b9d)", "iconname": "hel", "iconpic": "https://firebasestorage.googleapis.com/v0/b/converttoapp.appspot.com/o/images%2Fbb0c0179-1a8e-46e1-b690-7d23a0442ee0?alt=media&token=e2828d10-7fee-414e-9c11-82afb2298e12", "pid": "G4ftDZJx0Ew5FId5GrWv", "splashcolor": "Color(0xffffffff)", "splashpic": "https://firebasestorage.googleapis.com/v0/b/converttoapp.appspot.com/o/images%2Fbb0c0179-1a8e-46e1-b690-7d23a0442ee0?alt=media&token=e2828d10-7fee-414e-9c11-82afb2298e12", "uid": "fTdqNOMXDGacohZNzV29QFlqvUn2", "url": "https://matious.com"}